LICENSE.txt
README.md
setup.cfg
setup.py
dcmetro.egg-info/PKG-INFO
dcmetro.egg-info/SOURCES.txt
dcmetro.egg-info/dependency_links.txt
dcmetro.egg-info/entry_points.txt
dcmetro.egg-info/requires.txt
dcmetro.egg-info/top_level.txt
src/__init__.py
src/main/__init__.py
src/main/app.py
src/main/build_graph.py
src/main/commands.py
src/main/constants.py
src/main/dijkstra.py
src/main/generate_station_codes.py
src/main/get_station_distances.py