Metadata-Version: 2.1
Name: dcmetro
Version: 0.1.0
Summary: Console app for sending commands to get live information on the DC Metro
Author: Harun Feraidon
License: MIT
License-File: LICENSE.txt
